mvin-0.11.0b1.dist-info/METADATA
mvin-0.11.0b1.dist-info/WHEEL
mvin-0.11.0b1.dist-info/entry_points.txt
mvin-0.11.0b1.dist-info/licenses/LICENSE_APACHE
mvin-0.11.0b1.dist-info/licenses/LICENSE_MIT
mvin/__init__.py
mvin/excel_ops.py
mvin/functions/__init__.py
mvin/functions/excel_lib.py
mvin/interpreter.py
mvin-0.11.0b1.dist-info/RECORD
