Metadata-Version: 2.4
Name: mvin
Version: 0.11.0b1
Summary: Minimum Viable Interpreter (for single Excel formulas)
Author-Email: Jose Gonzalo Covarrubias <gocova.dev@gmail.com>
License-Expression: MIT OR Apache-2.0
License-File: LICENSE_APACHE
License-File: LICENSE_MIT
Classifier: Programming Language :: Python :: 3
Classifier: Programming Language :: Python :: 3.9
Classifier: Programming Language :: Python :: 3.10
Classifier: Programming Language :: Python :: 3.11
Classifier: Programming Language :: Python :: 3.12
Classifier: Programming Language :: Python :: 3.13
Classifier: Development Status :: 4 - Beta
Requires-Python: <4.0,>=3.9
